[{"name":"todoisttasktrigger","label":"Task Trigger","description":"Task Trigger","minimumControlRoomVersion":"8750","minimumBotAgentVersion":"20.11","mainClass":"com.automationanywhere.botcommand.samples.commands.basic.TaskTriggerTrigger","icon":"todo.svg","returnType":"RECORD","returnSubtype":"UNDEFINED","returnLabel":"","returnRequired":false,"returnDescription":"Available keys: triggerType, id","returnName":"TriggerData","attributes":[{"name":"token","label":"API token","type":"CREDENTIAL","rules":[{"name":"NOT_EMPTY"}]},{"name":"interval","label":"Please provide the interval to trigger in seconds","type":"NUMBER","defaultValue":{"number":"120","type":"NUMBER"},"rules":[{"name":"NOT_EMPTY"},{"name":"GREATER_THAN","value":"0"},{"name":"NUMBER_INTEGER"}]}]}]